{"Images": [{"Name": "i0", "Description": "", "Path": "images/test2", "Width": 1978, "Height": 1978, "MaxLevel": 0}], "Header": "", "Rotation": 0, "Layout": {"Grid": [["i0"]]}, "Stories": [{"Name": "", "Description": "", "Waypoints": [{"Name": "", "Description": "", "Arrows": [], "Overlays": [], "Group": "CD3", "Masks": [], "ActiveMasks": [], "Zoom": 0.9604687500000001, "Pan": [0.9815357084756793, 0.8505520712274176], "VisCanvasScatterplot": {"data": "data\\scatterplot.csv", "axes": {"x": "", "y": ""}, "clusters": {"labels": "", "reorder": "", "colors": ""}}}]}], "Masks": [], "Groups": [{"Name": "filaments", "Path": "filaments_0__vimentin--1__Pan-Cytokeratin--2__Keratin-14--3__Keratin-19--4__EGFR", "Colors": ["ff0000", "0000ff", "00ff00", "ff7f00", "ff00ff"], "Channels": ["vimentin", "Pan Cytokeratin", "Keratin 14", "Keratin 19", "EGFR"]}, {"Name": "immuno maker", "Path": "immuno-maker_5__CD3--6__CD4--7__CD8--8__CD20--9__PD-L1--10__PD1", "Colors": ["d0d620", "437e0d", "2ad3c5", "5e16b8", "64f40c", "74743b"], "Channels": ["CD3", "CD4", "CD8", "CD20", "PD-L1", "PD1"]}, {"Name": "vimentin", "Path": "vimentin_0__vimentin", "Colors": ["ff0000"], "Channels": ["vimentin"]}, {"Name": "Pan Cytokeratin", "Path": "Pan-Cytokeratin_1__Pan-Cytokeratin", "Colors": ["0000ff"], "Channels": ["Pan Cytokeratin"]}, {"Name": "Keratin 14", "Path": "Keratin-14_2__Keratin-14", "Colors": ["00ff00"], "Channels": ["Keratin 14"]}, {"Name": "Keratin 19", "Path": "Keratin-19_3__Keratin-19", "Colors": ["ff7f00"], "Channels": ["Keratin 19"]}, {"Name": "EGFR", "Path": "EGFR_4__EGFR", "Colors": ["ff00ff"], "Channels": ["EGFR"]}, {"Name": "CD3", "Path": "CD3_5__CD3", "Colors": ["d0d620"], "Channels": ["CD3"]}, {"Name": "CD4", "Path": "CD4_6__CD4", "Colors": ["437e0d"], "Channels": ["CD4"]}, {"Name": "CD8a", "Path": "CD8a_7__CD8", "Colors": ["2ad3c5"], "Channels": ["CD8"]}, {"Name": "CD20", "Path": "CD20_8__CD20", "Colors": ["5e16b8"], "Channels": ["CD20"]}, {"Name": "PD-L1", "Path": "PD-L1_9__PD-L1", "Colors": ["64f40c"], "Channels": ["PD-L1"]}, {"Name": "PD-1", "Path": "PD-1_10__PD1", "Colors": ["74743b"], "Channels": ["PD1"]}]}